examples/__init__.py
examples/swap_router/__init__.py
examples/swap_router/swap.py
examples/v2/__init__.py
examples/v2/sneak_preview.py
examples/v2/utils.py
examples/v2/tutorial/01_generate_account.py
examples/v2/tutorial/02_create_assets.py
examples/v2/tutorial/03_bootstrap_pool.py
examples/v2/tutorial/04_add_initial_liquidity.py
examples/v2/tutorial/05_add_flexible_liquidity.py
examples/v2/tutorial/06_add_single_asset_liquidity.py
examples/v2/tutorial/07_remove_liquidity.py
examples/v2/tutorial/08_single_asset_remove_liquidity.py
examples/v2/tutorial/09_fixed_input_swap.py
examples/v2/tutorial/10_fixed_output_swap.py
examples/v2/tutorial/11_flash_loan_1_single_asset.py
examples/v2/tutorial/12_flash_loan_2_multiple_assets.py
examples/v2/tutorial/13_flash_swap_1_pay_in_other_currency.py
examples/v2/tutorial/14_flash_swap_2_pay_in_same_currency.py
examples/v2/tutorial/15_flash_swap_3_pay_in_multiple_currencies.py
examples/v2/tutorial/__init__.py
examples/v2/tutorial/common.py
tests/__init__.py
tests/test_app_call_note.py
tests/swap_router/__init__.py
tests/swap_router/test.py
tests/v2/__init__.py
tests/v2/test_add_liquidity.py
tests/v2/test_bootstrap.py
tests/v2/test_flash_loan.py
tests/v2/test_flash_swap.py
tests/v2/test_remove_liquidity.py
tests/v2/test_swap.py
tinyman/__init__.py
tinyman/assets.py
tinyman/client.py
tinyman/compat.py
tinyman/errors.py
tinyman/exceptions.py
tinyman/optin.py
tinyman/tealishmap.py
tinyman/utils.py
tinyman/staking/__init__.py
tinyman/staking/constants.py
tinyman/swap_router/__init__.py
tinyman/swap_router/constants.py
tinyman/swap_router/management.py
tinyman/swap_router/routes.py
tinyman/swap_router/swap_router.py
tinyman/swap_router/utils.py
tinyman/v1/__init__.py
tinyman/v1/asc.json
tinyman/v1/bootstrap.py
tinyman/v1/burn.py
tinyman/v1/client.py
tinyman/v1/constants.py
tinyman/v1/contracts.py
tinyman/v1/fees.py
tinyman/v1/mint.py
tinyman/v1/optout.py
tinyman/v1/pools.py
tinyman/v1/redeem.py
tinyman/v1/swap.py
tinyman/v1/utils.py
sn0wyq_tinyman_py_sdk-2.2.0.dist-info/LICENSE
sn0wyq_tinyman_py_sdk-2.2.0.dist-info/METADATA
sn0wyq_tinyman_py_sdk-2.2.0.dist-info/WHEEL
sn0wyq_tinyman_py_sdk-2.2.0.dist-info/top_level.txt
sn0wyq_tinyman_py_sdk-2.2.0.dist-info/RECORD
