Metadata-Version: 2.1
Name: sn0wyq-tinyman-py-sdk
Version: 2.2.0
Summary: Tinyman Python SDK (forked)
Author: Tinyman
Author-email: hello@tinyman.org
License: MIT
Project-URL: Source, https://github.com/tinyman/tinyman-py-sdk
Requires-Python: >=3.8
License-File: LICENSE
Requires-Dist: py-algorand-sdk >=1.10.0
Requires-Dist: requests >=2.0.0
